MLProcessFlow/__init__.py
MLProcessFlow-0.0.1.dist-info/LICENSE.txt
MLProcessFlow-0.0.1.dist-info/METADATA
MLProcessFlow-0.0.1.dist-info/WHEEL
MLProcessFlow-0.0.1.dist-info/top_level.txt
MLProcessFlow-0.0.1.dist-info/RECORD
