Metadata-Version: 2.1
Name: MLProcessFlow
Version: 0.0.1
Summary: ML Process Flow
Home-page: UNKNOWN
Author: Riddhi
Author-email: UNKNOWN
License: UNKNOWN
Platform: UNKNOWN
Requires-Dist: pandas
